pys2let-2.2.7.dist-info/RECORD
pys2let-2.2.7.dist-info/WHEEL
pys2let-2.2.7.dist-info/METADATA
pys2let-2.2.7.dist-info/licenses/LICENSE
pys2let/CMakeLists.txt
pys2let/pys2let.pyx
pys2let/__init__.py
pys2let/pys2let.cpython-310-darwin.so
pys2let/plots.py
