Metadata-Version: 2.4
Name: pys2let
Version: 2.2.7
Summary: Fast wavelet transforms on the sphere
Keywords: numerical transforms,signal processing,science
Author: Jason D. McEwen, Chris R. G. Wallis, Martin Büttner, Jennifer Chan, Boris Leistedt
License-Expression: GPL-3.0-or-later
Project-URL: Homepage, http://astro-informatics.github.io/s2let/
Project-URL: Repository, http://github.com/astro-informatics/s2let.git
Project-URL: Issues, http://github.com/astro-informatics/s2let/issues
Requires-Python: >=3.8
Requires-Dist: numpy
Requires-Dist: scipy
Provides-Extra: plots
Requires-Dist: healpy; extra == "plots"
